{
  "project_info": {
    "project_number": "721544162238",
    "project_id": "flutterwithfirebase-40a78",
    "storage_bucket": "flutterwithfirebase-40a78.appspot.com"
  },
  "client": [
    {
      "client_info": {
        "mobilesdk_app_id": "1:721544162238:android:9c787e759b0ce5dccee7ef",
        "android_client_info": {
          "package_name": "com.example.firebase_setup"
        }
      },
      "oauth_client": [],
      "api_key": [
        {
          "current_key": "AIzaSyDj-2KONFzzcT0onBOpHl0cL_uNL8kj-qg"
        }
      ],
      "services": {
        "appinvite_service": {
          "other_platform_oauth_client": []
        }
      }
    }
  ],
  "configuration_version": "1"
}